litie/__about__.py
litie/__init__.py
litie/arguments.py
litie/losses.py
litie/registry.py
litie/callbacks/__init__.py
litie/callbacks/adversarial.py
litie/callbacks/logger.py
litie/datasets/__init__.py
litie/datasets/base.py
litie/datasets/iterable.py
litie/datasets/utils.py
litie/datasets/ee/__init__.py
litie/datasets/ee/base.py
litie/datasets/ee/gplinker.py
litie/datasets/ner/__init__.py
litie/datasets/ner/base.py
litie/datasets/ner/cnn.py
litie/datasets/ner/crf.py
litie/datasets/ner/global_pointer.py
litie/datasets/ner/lear.py
litie/datasets/ner/mrc.py
litie/datasets/ner/span.py
litie/datasets/ner/tplinker.py
litie/datasets/ner/w2ner.py
litie/datasets/re/__init__.py
litie/datasets/re/base.py
litie/datasets/re/casrel.py
litie/datasets/re/gplinker.py
litie/datasets/re/grte.py
litie/datasets/re/onerel.py
litie/datasets/re/pfn.py
litie/datasets/re/prgc.py
litie/datasets/re/spn.py
litie/datasets/re/tplinker.py
litie/datasets/uie/__init__.py
litie/datasets/uie/data.py
litie/datasets/uie/doccano.py
litie/datasets/uie/utils.py
litie/engines/__init__.py
litie/engines/base.py
litie/engines/ee.py
litie/engines/ner.py
litie/engines/re.py
litie/engines/uie.py
litie/layers/__init__.py
litie/layers/conv.py
litie/layers/crf.py
litie/layers/dropouts.py
litie/layers/global_pointer.py
litie/layers/layer_norm.py
litie/layers/lear.py
litie/layers/pfn.py
litie/layers/pooling.py
litie/layers/position.py
litie/layers/set_decoder.py
litie/layers/transformer.py
litie/layers/utils.py
litie/metrics/__init__.py
litie/metrics/base.py
litie/metrics/extraction/__init__.py
litie/metrics/extraction/precision_recall_fscore.py
litie/metrics/extraction/score.py
litie/metrics/extraction/span.py
litie/models/__init__.py
litie/models/base.py
litie/models/ee.py
litie/models/ner.py
litie/models/re.py
litie/models/uie.py
litie/nn/__init__.py
litie/nn/decode_utils.py
litie/nn/model_utils.py
litie/nn/chinese_bert/__init__.py
litie/nn/chinese_bert/configuration_chinese_bert.py
litie-1.0.1.dist-info/LICENSE
litie-1.0.1.dist-info/METADATA
litie-1.0.1.dist-info/WHEEL
litie-1.0.1.dist-info/top_level.txt
litie-1.0.1.dist-info/RECORD
